cannula/__init__.py
cannula/api.py
cannula/cli.py
cannula/context.py
cannula/directives.py
cannula/errors.py
cannula/format.py
cannula/py.typed
cannula/schema.py
cannula/schema_processor.py
cannula/types.py
cannula/utils.py
cannula/codegen/__init__.py
cannula/codegen/codegen.py
cannula/codegen/generate_context.py
cannula/codegen/generate_operations.py
cannula/codegen/generate_sql.py
cannula/codegen/generate_types.py
cannula/codegen/json_selection.py
cannula/codegen/parse_args.py
cannula/codegen/parse_type.py
cannula/codegen/parse_variables.py
cannula/codegen/schema_analyzer.py
cannula/contrib/__init__.py
cannula/contrib/asgi.py
cannula/contrib/config.py
cannula/contrib/otel.py
cannula/datasource/__init__.py
cannula/datasource/base.py
cannula/datasource/http.py
cannula/datasource/orm.py
cannula/handlers/application.py
cannula/handlers/asgi.py
cannula/handlers/const.py
cannula/handlers/operations.py
cannula/middleware/__init__.py
cannula/middleware/debug.py
cannula/middleware/profile.py
cannula/scalars/__init__.py
cannula/scalars/_base.py
cannula/scalars/date.py
cannula/scalars/util.py
cannula/statics/Makefile
cannula/statics/css/base.css
cannula/statics/css/base.min.css
cannula/statics/css/base.min.css.map
cannula/statics/js/components.js
cannula/statics/js/drawer.js
cannula/statics/js/lucide-icon.js
cannula/statics/js/theme-toggle.js
cannula-0.24.0.dist-info/METADATA
cannula-0.24.0.dist-info/WHEEL
cannula-0.24.0.dist-info/entry_points.txt
cannula-0.24.0.dist-info/licenses/LICENSE
cannula-0.24.0.dist-info/RECORD
