Metadata-Version: 2.4
Name: cannula
Version: 0.24.0
Summary: Async GraphQL Helper Library
Project-URL: Homepage, https://github.com/rmyers/cannula
Author-email: Robert Myers <robert@julython.org>
License-File: LICENSE
Keywords: graphql
Classifier: Development Status :: 4 - Beta
Classifier: License :: OSI Approved :: MIT License
Classifier: Operating System :: OS Independent
Classifier: Programming Language :: Python :: 3.10
Requires-Python: >=3.10
Requires-Dist: graphql-core<=3.2.6
Requires-Dist: pydantic>2.6
Requires-Dist: starlette<1.0
Provides-Extra: codegen
Requires-Dist: autoflake<=2.3.1; extra == 'codegen'
Requires-Dist: black<=25.1.0; extra == 'codegen'
Requires-Dist: jinja2<4.0; extra == 'codegen'
Requires-Dist: python-dotenv==1.0.1; extra == 'codegen'
Requires-Dist: tomli<=2.2.1; extra == 'codegen'
Requires-Dist: typing-extensions<=4.12.2; extra == 'codegen'
Provides-Extra: httpx
Requires-Dist: fastapi; extra == 'httpx'
Requires-Dist: httpx; extra == 'httpx'
Provides-Extra: performance
Requires-Dist: ariadne; extra == 'performance'
Requires-Dist: fastapi; extra == 'performance'
Requires-Dist: httpx; extra == 'performance'
Requires-Dist: pytest-asyncio; extra == 'performance'
Requires-Dist: pytest-cov; extra == 'performance'
Requires-Dist: pytest-httpx; extra == 'performance'
Requires-Dist: pytest-mock; extra == 'performance'
Requires-Dist: pytest<9; extra == 'performance'
Provides-Extra: test
Requires-Dist: aiosqlite==0.21.0; extra == 'test'
Requires-Dist: black; extra == 'test'
Requires-Dist: coverage==7.6.12; extra == 'test'
Requires-Dist: flake8==7.1.2; extra == 'test'
Requires-Dist: greenlet; extra == 'test'
Requires-Dist: hatch; extra == 'test'
Requires-Dist: mypy==1.15.0; extra == 'test'
Requires-Dist: opentelemetry-api~=1.0; extra == 'test'
Requires-Dist: opentelemetry-sdk~=1.0; extra == 'test'
Requires-Dist: pycodestyle; extra == 'test'
Requires-Dist: pydata-sphinx-theme; extra == 'test'
Requires-Dist: pytest-asyncio; extra == 'test'
Requires-Dist: pytest-cov; extra == 'test'
Requires-Dist: pytest-mock; extra == 'test'
Requires-Dist: pytest<9; extra == 'test'
Requires-Dist: python-dateutil==2.9.0; extra == 'test'
Requires-Dist: sphinx-argparse==0.5.2; extra == 'test'
Requires-Dist: sphinx-autodoc-typehints; extra == 'test'
Requires-Dist: sphinx==8.1.3; extra == 'test'
Requires-Dist: sqlalchemy==2.0.38; extra == 'test'
Requires-Dist: twine==6.1.0; extra == 'test'
Requires-Dist: types-python-dateutil; extra == 'test'
Requires-Dist: types-requests; extra == 'test'
Requires-Dist: uvicorn[standard]; extra == 'test'
